LICENSE
README.md
setup.cfg
setup.py
obstools/__init__.py
obstools.egg-info/PKG-INFO
obstools.egg-info/SOURCES.txt
obstools.egg-info/dependency_links.txt
obstools.egg-info/entry_points.txt
obstools.egg-info/requires.txt
obstools.egg-info/top_level.txt
obstools/atacr/__init__.py
obstools/atacr/classes.py
obstools/atacr/plotting.py
obstools/atacr/utils.py
obstools/comply/__init__.py
obstools/comply/classes.py
obstools/examples/meta/M08A.pkl
obstools/scripts/__init__.py
obstools/scripts/atacr_clean_spectra.py
obstools/scripts/atacr_correct_event.py
obstools/scripts/atacr_daily_spectra.py
obstools/scripts/atacr_download_data.py
obstools/scripts/atacr_download_data_xml.py
obstools/scripts/atacr_download_event.py
obstools/scripts/atacr_transfer_functions.py
obstools/scripts/comply_calculate.py
obstools/tests/__init__.py
obstools/tests/get_meta.py
obstools/tests/test_0_imports.py
obstools/tests/test_1_args.py
obstools/tests/test_2_a_scripts_noH.py
obstools/tests/test_2_b_scripts_noP.py
obstools/tests/test_2_c_scripts_all.py
obstools/tests/test_3_utils.py
obstools/tests/test_4_classes.py