Metadata-Version: 2.2
Name: obstools
Version: 0.1.4
Summary: Python tools for ocean bottom seismic instruments
Home-page: https://github.com/nfsi-canada/OBStools/archive/OBStools-0.1.4.tar.gz
Author: Pascal Audet, Helen Janiszewski
Author-email: pascal.audet@uottawa.ca
Maintainer: Pascal Audet, Helen Janiszewski
Maintainer-email: pascal.audet@uottawa.ca, hajanisz@hawaii.edu
Classifier: Development Status :: 3 - Alpha
Classifier: License :: OSI Approved :: MIT License
Classifier: Programming Language :: Python :: 3.6
Classifier: Programming Language :: Python :: 3.7
Classifier: Programming Language :: Python :: 3.8
Classifier: Programming Language :: Python :: 3.9
Requires-Python: >=3.6
License-File: LICENSE
Requires-Dist: numpy
Requires-Dist: obspy
Requires-Dist: stdb
Requires-Dist: scipy
Requires-Dist: pandas
Dynamic: author
Dynamic: author-email
Dynamic: classifier
Dynamic: home-page
Dynamic: maintainer
Dynamic: maintainer-email
Dynamic: requires-dist
Dynamic: requires-python
Dynamic: summary
